[{"line":1,"elements":[{"start_timestamp":"2023-04-14T19:17:36.754Z","line":14,"name":"TC03 radio","description":"","id":"checkbox-ve-radio-button;tc03-radio","type":"scenario","keyword":"Scenario","steps":[{"result":{"duration":3569587400,"status":"passed"},"line":15,"name":"kullanici \"https://testcenter.techproeducation.com/index.php?page=radio-buttons\" adresine gider","match":{"arguments":[{"val":"\"https://testcenter.techproeducation.com/index.php?page=radio-buttons\"","offset":10}],"location":"stepdefinitions.CommonStepDefinitions.kullanici_adresine_gider(java.lang.String)"},"keyword":"Given "},{"result":{"duration":273269300,"status":"passed"},"line":16,"name":"\"Football\" secili degilse sec","match":{"arguments":[{"val":"\"Football\"","offset":0}],"location":"stepdefinitions.TestCenterStepDefinitions.secili_degilse_sec(java.lang.String)"},"keyword":"And "},{"result":{"duration":997000,"status":"passed"},"line":17,"name":"sayfayi acik tutar","match":{"location":"stepdefinitions.CommonStepDefinitions.sayfayi_acik_tutar()"},"keyword":"And "}],"tags":[{"name":"@football"}]}],"name":"checkbox ve radio button","description":"","id":"checkbox-ve-radio-button","keyword":"Feature","uri":"file:src/test/resources/features/03_checkbox_radiobutton.feature","tags":[]}]